astromodels/__init__.py
astromodels/_version.py
astromodels/core/__init__.py
astromodels/core/cpickle_compatibility_layer.py
astromodels/core/memoization.py
astromodels/core/model.py
astromodels/core/model_parser.py
astromodels/core/my_yaml.py
astromodels/core/node_type.py
astromodels/core/parameter.py
astromodels/core/parameter_transformation.py
astromodels/core/polarization.py
astromodels/core/property.py
astromodels/core/serialization.py
astromodels/core/sky_direction.py
astromodels/core/spectral_component.py
astromodels/core/thread_safe_unit_format.py
astromodels/core/tree.py
astromodels/core/units.py
astromodels/data/past_1D_values.h5
astromodels/data/dark_matter/dmSpecTab.npy
astromodels/data/dark_matter/gammamc_dif.dat
astromodels/data/tests/black_hole.yaml
astromodels/data/tests/old_table.h5
astromodels/data/tests/simple_source.yaml
astromodels/data/tests/test.yaml
astromodels/data/tests/test_xspec_table_model.fits
astromodels/data/xsect/xsect_phabs_angr.fits
astromodels/data/xsect/xsect_phabs_aspl.fits
astromodels/data/xsect/xsect_tbabs_angr.fits
astromodels/data/xsect/xsect_tbabs_aspl.fits
astromodels/data/xsect/xsect_tbabs_wilm.fits
astromodels/data/xsect/xsect_wabs_angr.fits
astromodels/functions/__init__.py
astromodels/functions/function.py
astromodels/functions/functions_2D.py
astromodels/functions/functions_3D.py
astromodels/functions/numba_functions.py
astromodels/functions/priors.py
astromodels/functions/template_model.py
astromodels/functions/dark_matter/__init__.py
astromodels/functions/dark_matter/dm_models.py
astromodels/functions/functions_1D/__init__.py
astromodels/functions/functions_1D/absorption.py
astromodels/functions/functions_1D/apec.py
astromodels/functions/functions_1D/blackbody.py
astromodels/functions/functions_1D/extinction.py
astromodels/functions/functions_1D/functions.py
astromodels/functions/functions_1D/polynomials.py
astromodels/functions/functions_1D/powerlaws.py
astromodels/sources/__init__.py
astromodels-2.3.0.dev3.dist-info/LICENSE
astromodels-2.3.0.dev3.dist-info/METADATA
astromodels-2.3.0.dev3.dist-info/WHEEL
astromodels-2.3.0.dev3.dist-info/top_level.txt
astromodels-2.3.0.dev3.dist-info/RECORD
