Metadata-Version: 2.1
Name: astromodels
Version: 2.3.0.dev3
Summary: Astromodels contains models to be used in likelihood or Bayesian analysis in astronomy
Home-page: https://github.com/threeml/astromodels
Download-URL: https://github.com/threeml/astromodels/archive/v0.1
Author: Giacomo Vianello
Author-email: giacomo.vianello@gmail.com
License: UNKNOWN
Project-URL: Documentation, https://astromodels.readthedocs.io
Project-URL: Bug Tracker, https://github.com/threeML/astromodels/issues
Project-URL: Source Code, https://github.com/threeML/astromodels
Keywords: Likelihood,Models,fit
Platform: UNKNOWN
Classifier: Development Status :: 5 - Production/Stable
Classifier: Topic :: Scientific/Engineering :: Astronomy
Classifier: Intended Audience :: Science/Research
Classifier: Operating System :: POSIX
Classifier: Programming Language :: Python :: 2.7
Classifier: Programming Language :: Python :: 3.5
Classifier: Programming Language :: Python :: 3.6
Classifier: Programming Language :: Python :: 3.7
Classifier: Programming Language :: Python :: 3.8
Classifier: Environment :: Console
License-File: LICENSE
Requires-Dist: numpy (>=1.6)
Requires-Dist: PyYAML (>=5.1)
Requires-Dist: scipy (>=0.14)
Requires-Dist: astropy (>=1.2)
Requires-Dist: dill
Requires-Dist: future
Requires-Dist: interpolation
Requires-Dist: numba
Requires-Dist: h5py
Requires-Dist: pandas
Requires-Dist: tables
Requires-Dist: colorama
Requires-Dist: omegaconf
Provides-Extra: docs
Requires-Dist: sphinx (>=1.4) ; extra == 'docs'
Requires-Dist: sphinx-rtd-theme ; extra == 'docs'
Requires-Dist: nbsphinx ; extra == 'docs'
Requires-Dist: sphinx-autoapi ; extra == 'docs'
Provides-Extra: tests
Requires-Dist: pytest ; extra == 'tests'
